{
  "item-states": [
    {
      "folded": true,
      "id": "0e1d0yFbNhCi4sAIgvOwaDf"
    },
    {
      "folded": true,
      "id": "792f2yQiO1KaZce9Vn9zthN"
    },
    {
      "folded": true,
      "id": "1c5fc+yfAZOoodjqHeNPnzg"
    },
    {
      "folded": true,
      "id": "d0d21lBkq1HxaPaoT/ds0O5"
    },
    {
      "folded": true,
      "id": "8b92fYP6AVCH7dafRi643ah"
    },
    {
      "folded": true,
      "id": "af39dmDfe5Gu4UYhCsd6ugp"
    },
    {
      "folded": false,
      "id": "8cb6daiHbpKuZyFQ7toZ9ls"
    },
    {
      "folded": false,
      "id": "2190aDWOOJMopTo2LrgaAQr"
    },
    {
      "folded": true,
      "id": "88b4eHC21hFtYVqvaCZzPAt"
    },
    {
      "folded": true,
      "id": "b00759JClxA/Jpx6gBmFnpk"
    },
    {
      "folded": true,
      "id": "971d1geKjtFuaK5uyTuDWVe"
    },
    {
      "folded": true,
      "id": "8b117Y75bNPf4zfTqOwHOxz"
    },
    {
      "folded": true,
      "id": "16519NW8HBIdJjhU3fllf7I"
    }
  ]
}